{"stats":{"minecraft:dropped":{"minecraft:basalt":3},"minecraft:picked_up":{"minecraft:basalt":2},"minecraft:used":{"minecraft:spyglass":72,"minecraft:iron_pickaxe":11,"minecraft:goat_horn":6},"minecraft:mined":{"minecraft:basalt":11},"minecraft:custom":{"minecraft:sprint_one_cm":17064,"minecraft:time_since_rest":8196,"minecraft:walk_one_cm":10411,"minecraft:total_world_time":8196,"minecraft:leave_game":2,"minecraft:fly_one_cm":3948,"minecraft:crouch_one_cm":1229,"minecraft:sneak_time":691,"minecraft:play_time":8196,"minecraft:jump":61,"minecraft:time_since_death":8196,"minecraft:drop":3}},"DataVersion":4325}